cormo/placeholder.py
cormo-0.1.0.dist-info/LICENSE
cormo-0.1.0.dist-info/METADATA
cormo-0.1.0.dist-info/WHEEL
cormo-0.1.0.dist-info/RECORD
