Metadata-Version: 2.1
Name: cormo
Version: 0.1.0
Summary: General-purpose deterministic and Monte Carlo simulator
License: MIT
Keywords: monte carlo,simulation,flow management
Author: Armand Rego
Author-email: armand@weirdsheeplabs.com
Requires-Python: >=3.10,<4.0
Classifier: Development Status :: 2 - Pre-Alpha
Classifier: Intended Audience :: Developers
Classifier: Intended Audience :: Education
Classifier: Intended Audience :: Science/Research
Classifier: License :: OSI Approved :: MIT License
Classifier: Programming Language :: Python :: 3
Classifier: Programming Language :: Python :: 3.10
Classifier: Programming Language :: Python :: 3.11
Classifier: Programming Language :: Python :: 3.12
Requires-Dist: matplotlib (>=3.8.3,<4.0.0)
Requires-Dist: scipy (>=1.12.0,<2.0.0)
